CHANGES.txt
bootstrap.py
buildout.cfg
setup.py
hostout/__init__.py
hostout.cloud.egg-info/PKG-INFO
hostout.cloud.egg-info/SOURCES.txt
hostout.cloud.egg-info/dependency_links.txt
hostout.cloud.egg-info/entry_points.txt
hostout.cloud.egg-info/namespace_packages.txt
hostout.cloud.egg-info/not-zip-safe
hostout.cloud.egg-info/requires.txt
hostout.cloud.egg-info/top_level.txt
hostout/cloud/README.txt
hostout/cloud/__init__.py
hostout/cloud/fabfile.py
hostout/cloud/tests.py