Metadata-Version: 1.0
Name: hostout.cloud
Version: 1.0a5
Summary: all your hosts are belong to us!!!
Home-page: http://github.com/djay/hostout.cloud
Author: Dylan Jay
Author-email: software@pretaweb.com
License: UNKNOWN
Keywords: hostout
Platform: UNKNOWN
